{
  "users": [
    {
      "id": 2,
      "name": "Page Base",
      "emailAddress": "pbase1@booking.com",
      "address": "1 Stuart Circle"
    },
    {
      "id": 3,
      "name": "Daren Brine",
      "emailAddress": "dbrine2@examiner.com",
      "address": "777 Grim Avenue"
    },
    {
      "id": 4,
      "name": "Dorrie Necrews",
      "emailAddress": "dnecrews3@cnn.com",
      "address": "7102 Commercial Plaza"
    },
    {
      "id": 5,
      "name": "Josy Eskrigg",
      "emailAddress": "jeskrigg4@princeton.edu",
      "address": "2 Monica Court"
    },
    {
      "id": 6,
      "name": "Juana Brawn",
      "emailAddress": "jbrawn5@mozilla.org",
      "address": "64 Badeau Place"
    },
    {
      "id": 7,
      "name": "Ammamaria Fairney",
      "emailAddress": "afairney6@foxnews.com",
      "address": "892 Tomscot Trail"
    },
    {
      "id": 8,
      "name": "Fredia Ingree",
      "emailAddress": "fingree7@mayoclinic.com",
      "address": "63479 Namekagon Road"
    },
    {
      "id": 9,
      "name": "Juli Pigford",
      "emailAddress": "jpigford8@google.de",
      "address": "44 Bluestem Road"
    },
    {
      "id": 10,
      "name": "Mikey Kearton",
      "emailAddress": "mkearton9@dell.com",
      "address": "83 Graedel Way"
    },
    {
      "id": 11,
      "name": "Meggy Braune",
      "emailAddress": "mbraunea@weibo.com",
      "address": "88338 Sugar Lane"
    },
    {
      "id": 12,
      "name": "Karisa Dearl",
      "emailAddress": "kdearlb@cmu.edu",
      "address": "1 Lukken Court"
    },
    {
      "id": 14,
      "name": "Early Mordie",
      "emailAddress": "emordied@smh.com.au",
      "address": "324 Johnson Hill"
    },
    {
      "id": 15,
      "name": "Burnard Eady",
      "emailAddress": "beadye@economist.com",
      "address": "36594 Kim Road"
    },
    {
      "id": 16,
      "name": "Kariotta Zahor",
      "emailAddress": "kzahorf@prnewswire.com",
      "address": "767 Gulseth Point"
    },
    {
      "id": 17,
      "name": "Lorry Lillow",
      "emailAddress": "llillowg@livejournal.com",
      "address": "6 Blaine Center"
    },
    {
      "id": 18,
      "name": "Shaylynn Notman",
      "emailAddress": "snotmanh@vkontakte.ru",
      "address": "7 Eastlawn Hill"
    },
    {
      "id": 19,
      "name": "Caleb Branchett",
      "emailAddress": "cbranchetti@vimeo.com",
      "address": "183 Ludington Crossing"
    },
    {
      "id": 20,
      "name": "Sacha Lindroos",
      "emailAddress": "slindroosj@pbs.org",
      "address": "823 Lien Park"
    },
    {
      "id": 21,
      "name": "Forbes Streeton",
      "emailAddress": "fstreetonk@fda.gov",
      "address": "0505 Shasta Junction"
    },
    {
      "id": 22,
      "name": "Hamid Ravenscroftt",
      "emailAddress": "hravenscrofttl@nationalgeographic.com",
      "address": "866 Doe Crossing Parkway"
    },
    {
      "id": 23,
      "name": "Bonnee Peace",
      "emailAddress": "bpeacem@seesaa.net",
      "address": "0581 Onsgard Point"
    },
    {
      "id": 24,
      "name": "Ralina Eayrs",
      "emailAddress": "reayrsn@phpbb.com",
      "address": "9 Kim Hill"
    },
    {
      "id": 25,
      "name": "Noak Estcourt",
      "emailAddress": "nestcourto@marketwatch.com",
      "address": "617 Farmco Plaza"
    },
    {
      "id": 26,
      "name": "Tracey Gever",
      "emailAddress": "tgeverp@wsj.com",
      "address": "5149 Lyons Point"
    },
    {
      "id": 27,
      "name": "Pavla Hawson",
      "emailAddress": "phawsonq@storify.com",
      "address": "468 Gale Circle"
    },
    {
      "id": 28,
      "name": "Brigitte Caress",
      "emailAddress": "bcaressr@google.com.br",
      "address": "81291 Lerdahl Avenue"
    },
    {
      "id": 29,
      "name": "Scarface Godier",
      "emailAddress": "sgodiers@economist.com",
      "address": "2315 American Ash Trail"
    },
    {
      "id": 30,
      "name": "Dominique Blenkharn",
      "emailAddress": "dblenkharnt@eventbrite.com",
      "address": "1 Towne Trail"
    },
    {
      "id": 31,
      "name": "Amery Stedman",
      "emailAddress": "astedmanu@lycos.com",
      "address": "0 Erie Place"
    },
    {
      "id": 32,
      "name": "Jorgan Tweed",
      "emailAddress": "jtweedv@youtu.be",
      "address": "7445 Muir Hill"
    },
    {
      "id": 33,
      "name": "Hayley Marzella",
      "emailAddress": "hmarzellaw@myspace.com",
      "address": "4318 American Ash Pass"
    },
    {
      "id": 34,
      "name": "Heidi Curcher",
      "emailAddress": "hcurcherx@wisc.edu",
      "address": "87 Vera Center"
    },
    {
      "id": 35,
      "name": "Fritz Devine",
      "emailAddress": "fdeviney@eepurl.com",
      "address": "044 Dwight Drive"
    },
    {
      "id": 36,
      "name": "Cy O'Hallagan",
      "emailAddress": "cohallaganz@barnesandnoble.com",
      "address": "1 Barnett Junction"
    },
    {
      "id": 37,
      "name": "Kerry Smedmore",
      "emailAddress": "ksmedmore10@bigcartel.com",
      "address": "285 Porter Circle"
    },
    {
      "id": 38,
      "name": "Lynnett Broomhall",
      "emailAddress": "lbroomhall11@census.gov",
      "address": "1 Hollow Ridge Trail"
    },
    {
      "id": 39,
      "name": "Nanine Canizares",
      "emailAddress": "ncanizares12@hc360.com",
      "address": "65 Kropf Avenue"
    },
    {
      "id": 40,
      "name": "Valentijn McCowan",
      "emailAddress": "vmccowan13@sun.com",
      "address": "02 Birchwood Court"
    },
    {
      "id": 41,
      "name": "Sam Leebetter",
      "emailAddress": "sleebetter14@gmpg.org",
      "address": "1283 Prairie Rose Junction"
    },
    {
      "id": 42,
      "name": "Roobbie Fevier",
      "emailAddress": "rfevier15@joomla.org",
      "address": "4 Sheridan Center"
    },
    {
      "id": 43,
      "name": "Dyann Trayhorn",
      "emailAddress": "dtrayhorn16@yelp.com",
      "address": "337 High Crossing Terrace"
    },
    {
      "id": 44,
      "name": "Les Rous",
      "emailAddress": "lrous17@baidu.com",
      "address": "549 Main Pass"
    },
    {
      "id": 45,
      "name": "Morissa Croson",
      "emailAddress": "mcroson18@newyorker.com",
      "address": "8 Northwestern Road"
    },
    {
      "id": 46,
      "name": "Glenden Tease",
      "emailAddress": "gtease19@themeforest.net",
      "address": "17109 Kings Place"
    },
    {
      "id": 47,
      "name": "Milty Summerell",
      "emailAddress": "msummerell1a@mayoclinic.com",
      "address": "69 Karstens Park"
    },
    {
      "id": 48,
      "name": "Arlinda Flannery",
      "emailAddress": "aflannery1b@mysql.com",
      "address": "19 Anniversary Pass"
    },
    {
      "id": 49,
      "name": "Tammie Chipchase",
      "emailAddress": "tchipchase1c@ucsd.edu",
      "address": "8400 Ryan Court"
    },
    {
      "id": 50,
      "name": "Carmelita Abrehart",
      "emailAddress": "cabrehart1d@amazonaws.com",
      "address": "95 Montana Plaza"
    },
    {
      "id": 51,
      "name": "Gena Connichie",
      "emailAddress": "gconnichie1e@tinyurl.com",
      "address": "04 Anthes Lane"
    },
    {
      "id": 52,
      "name": "Anne Hollingby",
      "emailAddress": "ahollingby1f@wordpress.com",
      "address": "03 Autumn Leaf Alley"
    },
    {
      "id": 53,
      "name": "Bettine Hinsche",
      "emailAddress": "bhinsche1g@wikia.com",
      "address": "76995 Menomonie Park"
    },
    {
      "id": 54,
      "name": "Tammi Sedgefield",
      "emailAddress": "tsedgefield1h@flickr.com",
      "address": "937 Forest Run Junction"
    },
    {
      "id": 55,
      "name": "Raddie Jacobi",
      "emailAddress": "rjacobi1i@arizona.edu",
      "address": "31 Gerald Junction"
    },
    {
      "id": 56,
      "name": "Berne Reinisch",
      "emailAddress": "breinisch1j@eventbrite.com",
      "address": "6229 John Wall Way"
    },
    {
      "id": 57,
      "name": "Christi Wallach",
      "emailAddress": "cwallach1k@sbwire.com",
      "address": "948 Kinsman Circle"
    },
    {
      "id": 58,
      "name": "Marcie Bulpitt",
      "emailAddress": "mbulpitt1l@ifeng.com",
      "address": "192 Cordelia Junction"
    },
    {
      "id": 59,
      "name": "Lionel Harpham",
      "emailAddress": "lharpham1m@mapquest.com",
      "address": "1324 Cordelia Alley"
    },
    {
      "id": 60,
      "name": "Hestia Kidgell",
      "emailAddress": "hkidgell1n@hibu.com",
      "address": "2 Ramsey Alley"
    },
    {
      "id": 61,
      "name": "Rab Polendine",
      "emailAddress": "rpolendine1o@about.com",
      "address": "8 Pankratz Lane"
    },
    {
      "id": 62,
      "name": "Olin Kupper",
      "emailAddress": "okupper1p@weebly.com",
      "address": "2 Armistice Alley"
    },
    {
      "id": 63,
      "name": "Colene Acum",
      "emailAddress": "cacum1q@epa.gov",
      "address": "92449 Morrow Pass"
    },
    {
      "id": 64,
      "name": "Sarah Piddocke",
      "emailAddress": "spiddocke1r@sina.com.cn",
      "address": "96717 Melody Plaza"
    },
    {
      "id": 65,
      "name": "Clemente Roebuck",
      "emailAddress": "croebuck1s@mit.edu",
      "address": "5 Eastwood Park"
    },
    {
      "id": 66,
      "name": "Trevar Aslen",
      "emailAddress": "taslen1t@soundcloud.com",
      "address": "908 Talisman Park"
    },
    {
      "id": 67,
      "name": "Merv Greystock",
      "emailAddress": "mgreystock1u@ning.com",
      "address": "1781 Marquette Lane"
    },
    {
      "id": 68,
      "name": "Rogerio Seebright",
      "emailAddress": "rseebright1v@jimdo.com",
      "address": "971 Continental Center"
    },
    {
      "id": 69,
      "name": "Genovera Mishow",
      "emailAddress": "gmishow1w@bigcartel.com",
      "address": "7741 Redwing Alley"
    },
    {
      "id": 70,
      "name": "Davita Southcott",
      "emailAddress": "dsouthcott1x@ed.gov",
      "address": "3195 Barby Center"
    },
    {
      "id": 71,
      "name": "Valentina Grugerr",
      "emailAddress": "vgrugerr1y@yale.edu",
      "address": "9704 Merrick Drive"
    },
    {
      "id": 72,
      "name": "Rudie Pacquet",
      "emailAddress": "rpacquet1z@lycos.com",
      "address": "1 Saint Paul Park"
    },
    {
      "id": 73,
      "name": "Etti Burles",
      "emailAddress": "eburles20@stanford.edu",
      "address": "34033 Shasta Hill"
    },
    {
      "id": 74,
      "name": "Sarine Starbuck",
      "emailAddress": "sstarbuck21@odnoklassniki.ru",
      "address": "284 Novick Junction"
    },
    {
      "id": 75,
      "name": "Lucie Monksfield",
      "emailAddress": "lmonksfield22@w3.org",
      "address": "487 Columbus Terrace"
    },
    {
      "id": 76,
      "name": "Christiano Roughey",
      "emailAddress": "croughey23@ovh.net",
      "address": "514 Transport Lane"
    },
    {
      "id": 77,
      "name": "Lizzy Di Lucia",
      "emailAddress": "ldi24@amazon.co.jp",
      "address": "895 Gerald Place"
    },
    {
      "id": 78,
      "name": "Howie Benge",
      "emailAddress": "hbenge25@google.de",
      "address": "45 Towne Parkway"
    },
    {
      "id": 79,
      "name": "Britte Archanbault",
      "emailAddress": "barchanbault26@sohu.com",
      "address": "81220 Vahlen Point"
    },
    {
      "id": 80,
      "name": "Tiffie Rosenfelder",
      "emailAddress": "trosenfelder27@biblegateway.com",
      "address": "05998 Northfield Circle"
    },
    {
      "id": 81,
      "name": "Felisha Bunworth",
      "emailAddress": "fbunworth28@ibm.com",
      "address": "4 Steensland Place"
    },
    {
      "id": 82,
      "name": "Eloisa New",
      "emailAddress": "enew29@theglobeandmail.com",
      "address": "687 Birchwood Pass"
    },
    {
      "id": 83,
      "name": "Keeley Charter",
      "emailAddress": "kcharter2a@4shared.com",
      "address": "60029 Clove Drive"
    },
    {
      "id": 84,
      "name": "Janeen Yitzowitz",
      "emailAddress": "jyitzowitz2b@xrea.com",
      "address": "88 Thierer Park"
    },
    {
      "id": 85,
      "name": "Mallory Gelly",
      "emailAddress": "mgelly2c@paypal.com",
      "address": "01914 Grayhawk Drive"
    },
    {
      "id": 86,
      "name": "Tyson Teece",
      "emailAddress": "tteece2d@godaddy.com",
      "address": "17 Walton Park"
    },
    {
      "id": 87,
      "name": "Dirk Bigg",
      "emailAddress": "dbigg2e@foxnews.com",
      "address": "7438 Blue Bill Park Road"
    },
    {
      "id": 88,
      "name": "Noach Cud",
      "emailAddress": "ncud2f@trellian.com",
      "address": "4138 Cherokee Way"
    },
    {
      "id": 89,
      "name": "Elwira Corps",
      "emailAddress": "ecorps2g@instagram.com",
      "address": "1 Lukken Drive"
    },
    {
      "id": 90,
      "name": "Moshe Tredget",
      "emailAddress": "mtredget2h@ca.gov",
      "address": "880 Corry Pass"
    },
    {
      "id": 91,
      "name": "Galvin Mingame",
      "emailAddress": "gmingame2i@blogs.com",
      "address": "1080 Mesta Plaza"
    },
    {
      "id": 92,
      "name": "Catherin Schrader",
      "emailAddress": "cschrader2j@t.co",
      "address": "589 Dwight Park"
    },
    {
      "id": 93,
      "name": "Karylin Mordie",
      "emailAddress": "kmordie2k@skyrock.com",
      "address": "71750 Mifflin Pass"
    },
    {
      "id": 94,
      "name": "Amy Bladon",
      "emailAddress": "abladon2l@aol.com",
      "address": "6642 Florence Center"
    },
    {
      "id": 95,
      "name": "Claudianus Berriball",
      "emailAddress": "cberriball2m@studiopress.com",
      "address": "6 Northport Junction"
    },
    {
      "id": 96,
      "name": "Dennie Marquot",
      "emailAddress": "dmarquot2n@un.org",
      "address": "6266 Messerschmidt Pass"
    },
    {
      "id": 97,
      "name": "Maury Helbeck",
      "emailAddress": "mhelbeck2o@mysql.com",
      "address": "7143 Duke Parkway"
    },
    {
      "id": 98,
      "name": "Noach Chiles",
      "emailAddress": "nchiles2p@dmoz.org",
      "address": "5 Swallow Terrace"
    },
    {
      "id": 99,
      "name": "Aron Dowsey",
      "emailAddress": "adowsey2q@hhs.gov",
      "address": "3718 Loftsgordon Avenue"
    },
    {
      "id": 100,
      "name": "Conrade Bohman",
      "emailAddress": "cbohman2r@hexun.com",
      "address": "9 Farwell Place"
    }
  ]
}